netra/__init__.py
netra/anonymizer/__init__.py
netra/anonymizer/anonymizer.py
netra/anonymizer/base.py
netra/anonymizer/fp_anonymizer.py
netra/config.py
netra/dashboard/__init__.py
netra/dashboard/api.py
netra/dashboard/client.py
netra/dashboard/models.py
netra/decorators.py
netra/evaluation/__init__.py
netra/evaluation/api.py
netra/evaluation/client.py
netra/evaluation/context.py
netra/evaluation/models.py
netra/evaluation/utils.py
netra/exceptions/__init__.py
netra/exceptions/injection.py
netra/exceptions/pii.py
netra/exporters/__init__.py
netra/exporters/filtering_span_exporter.py
netra/exporters/trial_aware_otlp_exporter.py
netra/exporters/utils.py
netra/input_scanner.py
netra/instrumentation/__init__.py
netra/instrumentation/aiohttp/__init__.py
netra/instrumentation/aiohttp/version.py
netra/instrumentation/cartesia/__init__.py
netra/instrumentation/cartesia/utils.py
netra/instrumentation/cartesia/version.py
netra/instrumentation/cartesia/wrappers.py
netra/instrumentation/cerebras/__init__.py
netra/instrumentation/cerebras/utils.py
netra/instrumentation/cerebras/version.py
netra/instrumentation/cerebras/wrappers.py
netra/instrumentation/cohere/__init__.py
netra/instrumentation/cohere/version.py
netra/instrumentation/deepgram/__init__.py
netra/instrumentation/deepgram/utils.py
netra/instrumentation/deepgram/version.py
netra/instrumentation/deepgram/wrappers.py
netra/instrumentation/dspy/__init__.py
netra/instrumentation/dspy/utils.py
netra/instrumentation/dspy/version.py
netra/instrumentation/dspy/wrappers.py
netra/instrumentation/elevenlabs/__init__.py
netra/instrumentation/elevenlabs/utils.py
netra/instrumentation/elevenlabs/version.py
netra/instrumentation/elevenlabs/wrappers.py
netra/instrumentation/fastapi/__init__.py
netra/instrumentation/fastapi/version.py
netra/instrumentation/google_adk/__init__.py
netra/instrumentation/google_adk/utils.py
netra/instrumentation/google_adk/version.py
netra/instrumentation/google_adk/wrappers.py
netra_sdk-0.1.61.dist-info/METADATA
netra_sdk-0.1.61.dist-info/WHEEL
netra_sdk-0.1.61.dist-info/licenses/LICENCE
netra_sdk-0.1.61.dist-info/RECORD
