Metadata-Version: 2.4
Name: netra-sdk
Version: 0.1.61
Summary: A Python SDK for AI application observability that provides OpenTelemetry-based monitoring, tracing, and PII protection for LLM and vector database applications. Enables easy instrumentation, session tracking, and privacy-focused data collection for AI systems in production environments.
License-Expression: Apache-2.0
License-File: LICENCE
Keywords: netra,tracing,observability,sdk,ai,llm,vector,database
Author: Sooraj Thomas
Author-email: sooraj@keyvalue.systems
Requires-Python: >=3.10,<3.14
Classifier: Development Status :: 4 - Beta
Classifier: Framework :: OpenTelemetry
Classifier: Intended Audience :: Developers
Classifier: Programming Language :: Python
Classifier: Programming Language :: Python :: 3
Classifier: Programming Language :: Python :: 3.10
Classifier: Programming Language :: Python :: 3.11
Classifier: Programming Language :: Python :: 3.12
Classifier: Programming Language :: Python :: 3.13
Classifier: Typing :: Typed
Provides-Extra: presidio
Requires-Dist: dspy (>=3.0.3)
Requires-Dist: json-repair (==0.44.1)
Requires-Dist: opentelemetry-api (>=1.34.0,<2.0.0)
Requires-Dist: opentelemetry-instrumentation-aio-pika (>=0.55b1,<1.0.0)
Requires-Dist: opentelemetry-instrumentation-aiohttp-client (>=0.55b1,<1.0.0)
Requires-Dist: opentelemetry-instrumentation-aiokafka (>=0.55b1,<1.0.0)
Requires-Dist: opentelemetry-instrumentation-aiopg (>=0.55b1,<1.0.0)
Requires-Dist: opentelemetry-instrumentation-asyncclick (>=0.55b1,<1.0.0)
Requires-Dist: opentelemetry-instrumentation-asyncio (>=0.55b1,<1.0.0)
Requires-Dist: opentelemetry-instrumentation-asyncpg (>=0.55b1,<1.0.0)
Requires-Dist: opentelemetry-instrumentation-aws-lambda (>=0.55b1,<1.0.0)
Requires-Dist: opentelemetry-instrumentation-boto3sqs (>=0.55b1,<1.0.0)
Requires-Dist: opentelemetry-instrumentation-botocore (>=0.55b1,<1.0.0)
Requires-Dist: opentelemetry-instrumentation-cassandra (>=0.55b1,<1.0.0)
Requires-Dist: opentelemetry-instrumentation-celery (>=0.55b1,<1.0.0)
Requires-Dist: opentelemetry-instrumentation-click (>=0.55b1,<1.0.0)
Requires-Dist: opentelemetry-instrumentation-confluent-kafka (>=0.55b1,<1.0.0)
Requires-Dist: opentelemetry-instrumentation-django (>=0.55b1,<1.0.0)
Requires-Dist: opentelemetry-instrumentation-elasticsearch (>=0.55b1,<1.0.0)
Requires-Dist: opentelemetry-instrumentation-falcon (>=0.55b1,<1.0.0)
Requires-Dist: opentelemetry-instrumentation-fastapi (>=0.55b1,<1.0.0)
Requires-Dist: opentelemetry-instrumentation-flask (>=0.55b1,<1.0.0)
Requires-Dist: opentelemetry-instrumentation-grpc (>=0.55b1,<1.0.0)
Requires-Dist: opentelemetry-instrumentation-httpx (>=0.55b1,<1.0.0)
Requires-Dist: opentelemetry-instrumentation-jinja2 (>=0.55b1,<1.0.0)
Requires-Dist: opentelemetry-instrumentation-kafka-python (>=0.55b1,<1.0.0)
Requires-Dist: opentelemetry-instrumentation-logging (>=0.55b1,<1.0.0)
Requires-Dist: opentelemetry-instrumentation-mysql (>=0.55b1,<1.0.0)
Requires-Dist: opentelemetry-instrumentation-mysqlclient (>=0.55b1,<1.0.0)
Requires-Dist: opentelemetry-instrumentation-pika (>=0.55b1,<1.0.0)
Requires-Dist: opentelemetry-instrumentation-psycopg (>=0.55b1,<1.0.0)
Requires-Dist: opentelemetry-instrumentation-psycopg2 (>=0.55b1,<1.0.0)
Requires-Dist: opentelemetry-instrumentation-pymemcache (>=0.55b1,<1.0.0)
Requires-Dist: opentelemetry-instrumentation-pymongo (>=0.55b1,<1.0.0)
Requires-Dist: opentelemetry-instrumentation-pymssql (>=0.55b1,<1.0.0)
Requires-Dist: opentelemetry-instrumentation-pymysql (>=0.55b1,<1.0.0)
Requires-Dist: opentelemetry-instrumentation-redis (>=0.55b1,<1.0.0)
Requires-Dist: opentelemetry-instrumentation-remoulade (>=0.55b1,<1.0.0)
Requires-Dist: opentelemetry-instrumentation-requests (>=0.55b1,<1.0.0)
Requires-Dist: opentelemetry-instrumentation-sqlalchemy (>=0.55b1,<1.0.0)
Requires-Dist: opentelemetry-instrumentation-sqlite3 (>=0.55b1,<1.0.0)
Requires-Dist: opentelemetry-instrumentation-starlette (>=0.55b1,<1.0.0)
Requires-Dist: opentelemetry-instrumentation-system-metrics (>=0.55b1,<1.0.0)
Requires-Dist: opentelemetry-instrumentation-threading (>=0.55b1,<1.0.0)
Requires-Dist: opentelemetry-instrumentation-tornado (>=0.55b1,<1.0.0)
Requires-Dist: opentelemetry-instrumentation-tortoiseorm (>=0.55b1,<1.0.0)
Requires-Dist: opentelemetry-instrumentation-urllib (>=0.55b1,<1.0.0)
Requires-Dist: opentelemetry-instrumentation-urllib3 (>=0.55b1,<1.0.0)
Requires-Dist: opentelemetry-sdk (>=1.34.0,<2.0.0)
Requires-Dist: presidio-analyzer (==2.2.358) ; extra == "presidio"
Requires-Dist: presidio-anonymizer (==2.2.358) ; extra == "presidio"
Requires-Dist: stanza (>=1.10.1,<2.0.0) ; extra == "presidio"
Requires-Dist: traceloop-sdk (>=0.47.0,<0.48.0)
Requires-Dist: transformers (==4.51.3) ; extra == "presidio"
Project-URL: Changelog, https://github.com/KeyValueSoftwareSystems/netra-sdk-py/blob/main/CHANGELOG.md
Project-URL: Documentation, https://docs.getnetra.ai/introduction
Project-URL: Homepage, https://getnetra.ai/
Project-URL: Repository, https://github.com/KeyValueSoftwareSystems/netra-sdk-py
